[
    {
        "Timestamp": "8/22/2022 16:25:30",
        "Name": "sudarshan gautam",
        "Contact": "9843088182",
        "BloodGroup": "O+",
        "Location": "Sanepa, lalitpur",
        "Email Address": ""
    },
    {
        "Timestamp": "8/22/2022 16:28:42",
        "Name": "Shreedhar Pandey",
        "Contact": "9867736000",
        "BloodGroup": "B+",
        "Location": "Sanepa, Lalitpur",
        "Email Address": ""
    },
    {
        "Timestamp": "8/22/2022 16:30:46",
        "Name": "Roshan Khatri",
        "Contact": "9861284977",
        "BloodGroup": "B+",
        "Location": "sitapaila",
        "Email Address": ""
    },
    {
        "Timestamp": "8/22/2022 19:07:30",
        "Name": "Bikash Acharya",
        "Contact": "9849293949",
        "BloodGroup": "O+",
        "Location": "Thankot, Kathmandu",
        "Email Address": ""
    },
    {
        "Timestamp": "8/22/2022 20:02:20",
        "Name": "Manoj jung K.C.",
        "Contact": "9851133305",
        "BloodGroup": "A+",
        "Location": "Tokha-6, kathmandu",
        "Email Address": ""
    },
    {
        "Timestamp": "8/22/2022 20:04:59",
        "Name": "Ronit Sah",
        "Contact": "9804869682",
        "BloodGroup": "AB+",
        "Location": "Kupandole ",
        "Email Address": ""
    },
    {
        "Timestamp": "8/22/2022 20:08:20",
        "Name": "Samyam Aryal",
        "Contact": "9860541663",
        "BloodGroup": "B+",
        "Location": "Hadigaon",
        "Email Address": ""
    },
    {
        "Timestamp": "8/22/2022 20:16:19",
        "Name": "Ajay Ranabhat",
        "Contact": "9813510603",
        "BloodGroup": "O+",
        "Location": "Baneshor",
        "Email Address": ""
    },
    {
        "Timestamp": "8/22/2022 20:17:17",
        "Name": "Samjhana Thapa ",
        "Contact": "9862104667",
        "BloodGroup": "A+",
        "Location": "Kalanki, Kathmandu ",
        "Email Address": ""
    },
    {
        "Timestamp": "8/22/2022 20:20:32",
        "Name": "Sauri Ghimire ",
        "Contact": "9840174405",
        "BloodGroup": "O+",
        "Location": "Naikap, kathmandu",
        "Email Address": ""
    },
    {
        "Timestamp": "8/22/2022 20:21:31",
        "Name": "Sudip pandey",
        "Contact": "9865442435",
        "BloodGroup": "A+",
        "Location": "Koteshower",
        "Email Address": ""
    },
    {
        "Timestamp": "8/22/2022 20:22:49",
        "Name": "nawraj basnet",
        "Contact": "9819393106",
        "BloodGroup": "B+",
        "Location": "cheetrapati,kathmandu",
        "Email Address": ""
    },
    {
        "Timestamp": "8/22/2022 20:23:41",
        "Name": "Nikhil Neupane",
        "Contact": "9822839019",
        "BloodGroup": "A+",
        "Location": "Gwarko ",
        "Email Address": ""
    },
    {
        "Timestamp": "8/22/2022 20:24:39",
        "Name": "Nikhil Neupane",
        "Contact": "9822839019",
        "BloodGroup": "A+",
        "Location": "Imadol",
        "Email Address": ""
    },
    {
        "Timestamp": "8/22/2022 20:25:18",
        "Name": "shreesha bhatta",
        "Contact": "9866644695",
        "BloodGroup": "A -ve",
        "Location": "sankhamul,kathmandu",
        "Email Address": ""
    },
    {
        "Timestamp": "8/22/2022 20:26:47",
        "Name": "Shubham Raj Keshari ",
        "Contact": "9812089465",
        "BloodGroup": "O+",
        "Location": "Kalanki",
        "Email Address": ""
    },
    {
        "Timestamp": "8/22/2022 20:28:42",
        "Name": "Ashim Tiwari ",
        "Contact": "9846949001",
        "BloodGroup": "O+",
        "Location": "Permanent address Pokhara, Temporary in Kalanki ",
        "Email Address": ""
    },
    {
        "Timestamp": "8/22/2022 20:29:01",
        "Name": "Unique Neupane",
        "Contact": "9818624722",
        "BloodGroup": "O+",
        "Location": "Mephi",
        "Email Address": ""
    },
    {
        "Timestamp": "8/22/2022 20:29:17",
        "Name": "Upendra Regmi ",
        "Contact": "9840044274",
        "BloodGroup": "O+",
        "Location": "Kalanki",
        "Email Address": ""
    },
    {
        "Timestamp": "8/22/2022 20:30:42",
        "Name": "Dipesh Sedhai",
        "Contact": "9865010949",
        "BloodGroup": "A+",
        "Location": "Kalanki, kathmandu",
        "Email Address": ""
    },
    {
        "Timestamp": "8/22/2022 20:30:46",
        "Name": "Shijan Regmi",
        "Contact": "9860165509",
        "BloodGroup": "O+",
        "Location": "Bansbari",
        "Email Address": ""
    },
    {
        "Timestamp": "8/22/2022 20:32:10",
        "Name": "Aayush Basnet ",
        "Contact": "9842797591",
        "BloodGroup": "A+",
        "Location": "Bishal Chowk, Nakhipot, Lalitpur ",
        "Email Address": ""
    },
    {
        "Timestamp": "8/22/2022 20:32:50",
        "Name": "Rabiya Begum",
        "Contact": "9816688055",
        "BloodGroup": "B+",
        "Location": "Nayabato",
        "Email Address": ""
    },
    {
        "Timestamp": "8/22/2022 20:33:29",
        "Name": "Roshan Chaudhary ",
        "Contact": "9803282461",
        "BloodGroup": "O-",
        "Location": "Koteshwor ",
        "Email Address": ""
    },
    {
        "Timestamp": "8/22/2022 20:34:03",
        "Name": "Anirudra Dahal",
        "Contact": "9803042255",
        "BloodGroup": "B+",
        "Location": "Ekantakuna",
        "Email Address": ""
    },
    {
        "Timestamp": "8/22/2022 20:34:04",
        "Name": "Krishna Bahadur Pandey ",
        "Contact": "9818589716",
        "BloodGroup": "A+",
        "Location": "Samakhusi, Kathmandu ",
        "Email Address": ""
    },
    {
        "Timestamp": "8/22/2022 20:34:13",
        "Name": "Isha Shrestha",
        "Contact": "9841380504",
        "BloodGroup": "A+",
        "Location": "Kupondole, Lalitpur ",
        "Email Address": ""
    },
    {
        "Timestamp": "8/22/2022 20:34:38",
        "Name": "Norgen moktan",
        "Contact": "9813513864",
        "BloodGroup": "A+",
        "Location": "Komdol swoyambhu",
        "Email Address": ""
    },
    {
        "Timestamp": "8/22/2022 20:35:03",
        "Name": "Khagendra Singh Jora ",
        "Contact": "9812766153",
        "BloodGroup": "B+",
        "Location": "Kathmandu ",
        "Email Address": ""
    },
    {
        "Timestamp": "8/22/2022 20:36:07",
        "Name": "Rensa Neupane",
        "Contact": "9808024554",
        "BloodGroup": "AB+",
        "Location": "Sanepa",
        "Email Address": ""
    },
    {
        "Timestamp": "8/22/2022 20:36:14",
        "Name": "Rolamba Jung Budhathoki ",
        "Contact": "9869812995",
        "BloodGroup": "A+",
        "Location": "Mid baneshwor ",
        "Email Address": ""
    },
    {
        "Timestamp": "8/22/2022 20:36:45",
        "Name": "Sajja Aryal",
        "Contact": "9824962349",
        "BloodGroup": "O+",
        "Location": "Kalanki, Kathmandu",
        "Email Address": ""
    },
    {
        "Timestamp": "8/22/2022 20:37:04",
        "Name": "Basanta Neupane ",
        "Contact": "9818712445",
        "BloodGroup": "O+",
        "Location": "Thimi, Bhaktapur ",
        "Email Address": ""
    },
    {
        "Timestamp": "8/22/2022 20:37:42",
        "Name": "Tarzan Ghimire ",
        "Contact": "9810967545",
        "BloodGroup": "B+",
        "Location": "Thasikhel, Lalitpur",
        "Email Address": ""
    },
    {
        "Timestamp": "8/22/2022 20:40:08",
        "Name": "supreme adhikari",
        "Contact": "9860900914",
        "BloodGroup": "AB+",
        "Location": "balaju",
        "Email Address": ""
    },
    {
        "Timestamp": "8/22/2022 20:42:57",
        "Name": "Anish yadav",
        "Contact": "9811854099",
        "BloodGroup": "A+",
        "Location": "Imadol",
        "Email Address": ""
    },
    {
        "Timestamp": "8/22/2022 20:44:04",
        "Name": "Pravin Kumar Sah ",
        "Contact": "9865170280",
        "BloodGroup": "B+",
        "Location": "kalanki ",
        "Email Address": ""
    },
    {
        "Timestamp": "8/22/2022 20:46:19",
        "Name": "Suruchee Pokhrel ",
        "Contact": "9842796362",
        "BloodGroup": "O+",
        "Location": "Ekantakuna, Lalitpur ",
        "Email Address": ""
    },
    {
        "Timestamp": "8/22/2022 20:49:31",
        "Name": "Saroj Raut ",
        "Contact": "9816875293",
        "BloodGroup": "O-",
        "Location": "New Baneshwor ",
        "Email Address": ""
    },
    {
        "Timestamp": "8/22/2022 20:50:37",
        "Name": "Tushaka shrestha",
        "Contact": "9803933153",
        "BloodGroup": "A+",
        "Location": "Kathmandu",
        "Email Address": ""
    },
    {
        "Timestamp": "8/22/2022 20:56:32",
        "Name": "Pragyan Adhikari",
        "Contact": "9840252194",
        "BloodGroup": "A+",
        "Location": "bhaktapur",
        "Email Address": ""
    },
    {
        "Timestamp": "8/22/2022 20:57:54",
        "Name": "Birendra Kumar Tharu ",
        "Contact": "9822437552",
        "BloodGroup": "A+",
        "Location": "Khadka gaun",
        "Email Address": ""
    },
    {
        "Timestamp": "8/22/2022 20:58:57",
        "Name": "Aashutosh Subedi ",
        "Contact": "9861300613",
        "BloodGroup": "A+",
        "Location": "Boudha, Mahankal",
        "Email Address": ""
    },
    {
        "Timestamp": "8/22/2022 21:04:23",
        "Name": "SUBRAT HUMAGAIN",
        "Contact": "9843737760",
        "BloodGroup": "AB+",
        "Location": "KAUSHALTAR,BHAKTAPUR",
        "Email Address": ""
    },
    {
        "Timestamp": "8/22/2022 21:04:53",
        "Name": "Binit Nepal ",
        "Contact": "9866694644",
        "BloodGroup": "B+",
        "Location": "Butwal ",
        "Email Address": ""
    },
    {
        "Timestamp": "8/22/2022 21:09:24",
        "Name": "Rinky Shah ",
        "Contact": "9813788986",
        "BloodGroup": "B+",
        "Location": "Kalanki ",
        "Email Address": ""
    },
    {
        "Timestamp": "8/22/2022 21:11:48",
        "Name": "Rabin Basnet",
        "Contact": "9861386766",
        "BloodGroup": "O+",
        "Location": "Bagbazar",
        "Email Address": ""
    },
    {
        "Timestamp": "8/22/2022 21:13:11",
        "Name": "Pawan Pandey ",
        "Contact": "9847382342",
        "BloodGroup": "A+",
        "Location": "New Baneshwor",
        "Email Address": ""
    },
    {
        "Timestamp": "8/22/2022 21:13:42",
        "Name": "Shreeya Simkhada",
        "Contact": "9840364776",
        "BloodGroup": "O+",
        "Location": "Machhapokhari,Kathmandu",
        "Email Address": ""
    },
    {
        "Timestamp": "8/22/2022 21:14:33",
        "Name": "Aayush Adhikari",
        "Contact": "9860905270",
        "BloodGroup": "B+",
        "Location": "Thimi, Bhaktapur",
        "Email Address": ""
    },
    {
        "Timestamp": "8/22/2022 21:15:04",
        "Name": "Pragyan Neupane",
        "Contact": "9841531423",
        "BloodGroup": "AB+",
        "Location": "Mahadevstan",
        "Email Address": ""
    },
    {
        "Timestamp": "8/22/2022 21:18:34",
        "Name": "Gr Khatri ",
        "Contact": "9861369691",
        "BloodGroup": "B+",
        "Location": "Lalitpur ",
        "Email Address": ""
    },
    {
        "Timestamp": "8/22/2022 21:19:49",
        "Name": "Aayush Dangol",
        "Contact": "9810384095",
        "BloodGroup": "B+",
        "Location": "Kathmandu ",
        "Email Address": ""
    },
    {
        "Timestamp": "8/22/2022 21:22:15",
        "Name": "NawarajBashyal",
        "Contact": "9867724354",
        "BloodGroup": "A+",
        "Location": "kathmandu",
        "Email Address": ""
    },
    {
        "Timestamp": "8/22/2022 21:24:41",
        "Name": "SABIN K.C.",
        "Contact": "9863164710",
        "BloodGroup": "O+",
        "Location": "Kupandol ",
        "Email Address": ""
    },
    {
        "Timestamp": "8/22/2022 21:25:04",
        "Name": "Bisesh Shakya ",
        "Contact": "9813690346",
        "BloodGroup": "A+",
        "Location": "Kumaripati",
        "Email Address": ""
    },
    {
        "Timestamp": "8/22/2022 21:30:50",
        "Name": "Sita Gautam",
        "Contact": "9847085906",
        "BloodGroup": "O+",
        "Location": "kapilvastu",
        "Email Address": ""
    },
    {
        "Timestamp": "8/22/2022 21:31:46",
        "Name": "Tulsi Ram Gautam",
        "Contact": "9844711506",
        "BloodGroup": "O+",
        "Location": "kapilvastu",
        "Email Address": ""
    },
    {
        "Timestamp": "8/22/2022 21:32:44",
        "Name": "Jayanti Gautam",
        "Contact": "986-2448400",
        "BloodGroup": "O+",
        "Location": "Kapilvastu",
        "Email Address": ""
    },
    {
        "Timestamp": "8/22/2022 21:34:53",
        "Name": "Susan shrestha",
        "Contact": "9806701688",
        "BloodGroup": "A+",
        "Location": "satdobato",
        "Email Address": ""
    },
    {
        "Timestamp": "8/22/2022 21:38:20",
        "Name": "Robinson Pujara",
        "Contact": "9810630492",
        "BloodGroup": "O-",
        "Location": "Pepsicola,Kathmandu",
        "Email Address": ""
    },
    {
        "Timestamp": "8/22/2022 21:43:23",
        "Name": "Sweta Simkhada",
        "Contact": "9808377663",
        "BloodGroup": "O+",
        "Location": "Machhapokhari,kathmandu",
        "Email Address": ""
    },
    {
        "Timestamp": "8/22/2022 21:44:10",
        "Name": "Kalpana Paneru Simkhada",
        "Contact": "9840364776",
        "BloodGroup": "O+",
        "Location": "Machhapokhari,Kathmandu",
        "Email Address": ""
    },
    {
        "Timestamp": "8/22/2022 21:56:32",
        "Name": "Ujjwal Shrestha ",
        "Contact": "9869001579",
        "BloodGroup": "B+",
        "Location": "Gurjudhara ",
        "Email Address": ""
    },
    {
        "Timestamp": "8/22/2022 21:57:13",
        "Name": "Archana Subedi",
        "Contact": "9849934778",
        "BloodGroup": "A+",
        "Location": "Sankhamul",
        "Email Address": ""
    },
    {
        "Timestamp": "8/22/2022 21:59:06",
        "Name": "Rabin Shrestha ",
        "Contact": "9869097447",
        "BloodGroup": "B+",
        "Location": "Kalanki",
        "Email Address": ""
    },
    {
        "Timestamp": "8/22/2022 21:59:48",
        "Name": "Aavas Dahal",
        "Contact": "9861567721",
        "BloodGroup": "B+",
        "Location": "Gokarneshwor-7,Dakshin Dhoka",
        "Email Address": ""
    },
    {
        "Timestamp": "8/22/2022 22:01:55",
        "Name": "Subiddya ",
        "Contact": "9804484426",
        "BloodGroup": "B+",
        "Location": "Lalitpur",
        "Email Address": ""
    },
    {
        "Timestamp": "8/22/2022 22:06:49",
        "Name": "Anjil upreti",
        "Contact": "9840004872",
        "BloodGroup": "A+",
        "Location": "Naikap",
        "Email Address": ""
    },
    {
        "Timestamp": "8/22/2022 22:16:42",
        "Name": "Keshab Bhattarai",
        "Contact": "9843616795",
        "BloodGroup": "AB+",
        "Location": "Babarmahal",
        "Email Address": ""
    },
    {
        "Timestamp": "8/22/2022 22:23:11",
        "Name": "nishant duwadi",
        "Contact": "9860471426",
        "BloodGroup": "A+",
        "Location": "tarkeshwor, lolang height",
        "Email Address": ""
    },
    {
        "Timestamp": "8/22/2022 22:23:26",
        "Name": "Jinish Shrestha ",
        "Contact": "9861288980",
        "BloodGroup": "O+",
        "Location": "Dhumbarahi ",
        "Email Address": ""
    },
    {
        "Timestamp": "8/22/2022 22:24:26",
        "Name": "Ashish Dhakal",
        "Contact": "9822478044",
        "BloodGroup": "O+",
        "Location": "kirtipur,kathmandu",
        "Email Address": ""
    },
    {
        "Timestamp": "8/22/2022 22:31:55",
        "Name": "Samir Ghimire",
        "Contact": "9845854790",
        "BloodGroup": "O-",
        "Location": "Balkhu, Kathmandu",
        "Email Address": ""
    },
    {
        "Timestamp": "8/22/2022 22:35:51",
        "Name": "Aman kumar jha",
        "Contact": "9809632217",
        "BloodGroup": "A+",
        "Location": "Kupondole ",
        "Email Address": ""
    },
    {
        "Timestamp": "8/22/2022 23:13:40",
        "Name": "Nitesh Keshari ",
        "Contact": "9818287137",
        "BloodGroup": "O+",
        "Location": "Kalanki ",
        "Email Address": ""
    },
    {
        "Timestamp": "8/22/2022 23:25:43",
        "Name": "Prem khadka",
        "Contact": "9867177160",
        "BloodGroup": "O+",
        "Location": "kirtipur",
        "Email Address": ""
    },
    {
        "Timestamp": "8/22/2022 23:53:48",
        "Name": "Nirman kunwar",
        "Contact": "9846855448",
        "BloodGroup": "O+",
        "Location": "Dhovighat",
        "Email Address": ""
    },
    {
        "Timestamp": "8/23/2022 6:48:02",
        "Name": "Babina Banjara",
        "Contact": "9865997343",
        "BloodGroup": "B+",
        "Location": "Balaju",
        "Email Address": ""
    },
    {
        "Timestamp": "8/23/2022 7:06:09",
        "Name": "Muna bhusal",
        "Contact": "9867388621",
        "BloodGroup": "O+",
        "Location": "Butwal",
        "Email Address": ""
    },
    {
        "Timestamp": "8/23/2022 9:59:12",
        "Name": "Nikita Paudyal ",
        "Contact": "9869837498",
        "BloodGroup": "B+",
        "Location": "Kathmandu ",
        "Email Address": ""
    },
    {
        "Timestamp": "8/23/2022 14:25:34",
        "Name": "Binayak paudel",
        "Contact": "9864860266",
        "BloodGroup": "O+",
        "Location": "Sainamaina-6, ramapur-colony",
        "Email Address": ""
    },
    {
        "Timestamp": "8/23/2022 19:29:30",
        "Name": "Thomas Khawas ",
        "Contact": "9816317861",
        "BloodGroup": "O+",
        "Location": "Kathmandu ",
        "Email Address": ""
    },
    {
        "Timestamp": "8/23/2022 20:59:28",
        "Name": "Madhav Raj Shukla ",
        "Contact": "9817778205",
        "BloodGroup": "A+",
        "Location": "Kathmandu",
        "Email Address": ""
    },
    {
        "Timestamp": "8/23/2022 23:51:09",
        "Name": "Binay Shah",
        "Contact": "986-0477909 ",
        "BloodGroup": "A+",
        "Location": "Gwarko",
        "Email Address": ""
    },
    {
        "Timestamp": "8/24/2022 8:36:18",
        "Name": "Subash subedi",
        "Contact": "9845963409",
        "BloodGroup": "O+",
        "Location": "Ekantakuna,lalitpur",
        "Email Address": ""
    },
    {
        "Timestamp": "8/24/2022 19:15:48",
        "Name": "Bidhya Sagar Paudel",
        "Contact": "9849700644",
        "BloodGroup": "A+",
        "Location": "Nagarjun-1, Raniban, Ktm",
        "Email Address": ""
    },
    {
        "Timestamp": "8/24/2022 19:43:50",
        "Name": "Suman Sapkota",
        "Contact": "9869173416",
        "BloodGroup": "A+",
        "Location": "Thimi",
        "Email Address": ""
    },
    {
        "Timestamp": "8/24/2022 22:06:29",
        "Name": "Shubhanshu kumar bhagat",
        "Contact": "9817716099",
        "BloodGroup": "B+",
        "Location": "Kathmandu",
        "Email Address": ""
    },
    {
        "Timestamp": "8/25/2022 12:01:22",
        "Name": "Manish Rajbanshi",
        "Contact": "9807986498",
        "BloodGroup": "B+",
        "Location": "Sanepa",
        "Email Address": ""
    },
    {
        "Timestamp": "8/25/2022 17:38:32",
        "Name": "Abhijeet Thakur ",
        "Contact": "9851239496",
        "BloodGroup": "A+",
        "Location": "Gwarko, Imadole",
        "Email Address": ""
    },
    {
        "Timestamp": "1/10/2023 15:54:40",
        "Name": "Ramesh Yadav",
        "Contact": "+977 986-5388119",
        "BloodGroup": "O+",
        "Location": "Balkhu",
        "Email Address": ""
    },
    {
        "Timestamp": "1/10/2023 15:55:25",
        "Name": "Rujal Thapa",
        "Contact": "+977 988-6756279",
        "BloodGroup": "O-",
        "Location": "Boudha",
        "Email Address": ""
    },
    {
        "Timestamp": "1/10/2023 15:56:53",
        "Name": "sneha devkota",
        "Contact": "+977 982-5819311",
        "BloodGroup": "AB-",
        "Location": "basundhara",
        "Email Address": ""
    },
    {
        "Timestamp": "1/10/2023 15:57:51",
        "Name": "David Rawal",
        "Contact": "+977 986-8362448",
        "BloodGroup": "A -ve",
        "Location": "kalanki",
        "Email Address": ""
    },
    {
        "Timestamp": "1/10/2023 15:58:47",
        "Name": "samika Poudyal",
        "Contact": "+977 988-7512151",
        "BloodGroup": "O-",
        "Location": "Hattiban",
        "Email Address": ""
    },
    {
        "Timestamp": "1/10/2023 15:59:38",
        "Name": "manoj khatri",
        "Contact": "+977 970-3309473",
        "BloodGroup": "B-",
        "Location": "Baneshwor",
        "Email Address": ""
    },
    {
        "Timestamp": "1/10/2023 17:47:28",
        "Name": "Ram Gyawali",
        "Contact": "+977 960-0335526",
        "BloodGroup": "B+",
        "Location": "Koteshwor",
        "Email Address": ""
    },
    {
        "Timestamp": "1/10/2023 17:48:20",
        "Name": "Shyam Sundar Pandey",
        "Contact": " 982-9517629",
        "BloodGroup": "O+",
        "Location": "Gothatar",
        "Email Address": ""
    },
    {
        "Timestamp": "1/10/2023 17:49:09",
        "Name": "Amit Gautam",
        "Contact": "+977 974-2096649",
        "BloodGroup": "B-",
        "Location": "Kirtipur",
        "Email Address": ""
    },
    {
        "Timestamp": "1/10/2023 17:50:23",
        "Name": "Rishav Banjadey",
        "Contact": "980-2319125",
        "BloodGroup": "O-",
        "Location": "Kapan, Nepal",
        "Email Address": ""
    },
    {
        "Timestamp": "1/10/2023 17:51:35",
        "Name": "Deepak Chhetri",
        "Contact": "9704692166",
        "BloodGroup": "A+",
        "Location": "Machchhegaun",
        "Email Address": ""
    },
    {
        "Timestamp": "1/10/2023 17:53:16",
        "Name": "Aabesh acharya",
        "Contact": "988-6749272",
        "BloodGroup": "A -ve",
        "Location": "Gonggabu",
        "Email Address": ""
    },
    {
        "Timestamp": "1/10/2023 17:54:44",
        "Name": "Gagan Sapkota",
        "Contact": "986-2080388",
        "BloodGroup": "AB-",
        "Location": "Jorpati",
        "Email Address": ""
    },
    {
        "Timestamp": "1/10/2023 17:55:43",
        "Name": " Ishwar Kandel",
        "Contact": "988-9190914",
        "BloodGroup": "B+",
        "Location": "Kisandol",
        "Email Address": ""
    },
    {
        "Timestamp": "1/10/2023 17:57:08",
        "Name": " Kapil Bhattarai",
        "Contact": "988-2229534",
        "BloodGroup": "O+",
        "Location": "Budhanilkantha",
        "Email Address": ""
    },
    {
        "Timestamp": "1/10/2023 18:04:34",
        "Name": ".Madan Banskota",
        "Contact": "963-7453970",
        "BloodGroup": "B-",
        "Location": "Sankhu",
        "Email Address": ""
    }
]